{"meta":{"requests":338,"timestamp":1491335612,"status":200,"message":"Request successful","method_id":1291,"method":{}},"data":{"date":{"week":32,"year":2015,"start":"2015-08-03","end":"2015-08-07"},"outlets":[{"outlet_name":"Bon Appetit","outlet_id":3,"menu":[{"date":"2015-08-04","day":"Tuesday","meals":{"lunch":[{"product_name":"BA General TSO Chicken","product_id":2453,"diet_type":"Non Vegetarian"}],"dinner":[{"product_name":"DC, Spicy Beef with Vietnam style potatoes","product_id":2600,"diet_type":"Non Vegetarian"}]},"notes":null},{"date":"2015-08-05","day":"Wednesday","meals":{"lunch":[{"product_name":"BA, Tofu and Shrimp","product_id":2587,"diet_type":"Non Vegetarian"}],"dinner":[{"product_name":"DC, Pork Chop and Shrimp with Lemon Grass","product_id":2602,"diet_type":"Non Vegetarian"}]},"notes":null},{"date":"2015-08-06","day":"Thursday","meals":{"lunch":[{"product_name":"BA, King to Pork Chop","product_id":741,"diet_type":"Non Vegetarian"}],"dinner":[{"product_name":"DC, Roasted Chicken Leg with BBQ Sauce,","product_id":1154,"diet_type":"Non Vegetarian"}]},"notes":null},{"date":"2015-08-07","day":"Friday","meals":{"lunch":[{"product_name":"Chef special","product_id":null,"diet_type":null}],"dinner":[]},"notes":null}]},{"outlet_name":"Pastry Plus","outlet_id":23,"menu":[{"date":"2015-08-04","day":"Tuesday","meals":{"lunch":[{"product_name":"NH- Cream of mushroom","product_id":null,"diet_type":null},{"product_name":"NH- Roasted chicken noodle with herb","product_id":null,"diet_type":null}],"dinner":[]},"notes":null},{"date":"2015-08-05","day":"Wednesday","meals":{"lunch":[{"product_name":"NH- Chicken stew- entree","product_id":null,"diet_type":null},{"product_name":"NH- Cream of asparagus","product_id":null,"diet_type":null}],"dinner":[]},"notes":null},{"date":"2015-08-06","day":"Thursday","meals":{"lunch":[{"product_name":"NH- Split pea with ham","product_id":null,"diet_type":null},{"product_name":"NH- Tomato tortellini","product_id":null,"diet_type":null}],"dinner":[]},"notes":null},{"date":"2015-08-07","day":"Friday","meals":{"lunch":[{"product_name":"NH- Chicken corn chowder","product_id":null,"diet_type":null},{"product_name":"NH- Vegan vegetable","product_id":null,"diet_type":null}],"dinner":[]},"notes":null}]}]}}