{"meta":{"requests":950,"timestamp":1521842547,"status":200,"message":"Request successful","method_id":1297,"method":{}},"data":[{"date":"2017-10-30","outlet_name":"REVelation","outlet_id":7,"note":null},{"date":"2017-10-31","outlet_name":"REVelation","outlet_id":7,"note":null},{"date":"2017-11-01","outlet_name":"REVelation","outlet_id":7,"note":null},{"date":"2017-11-02","outlet_name":"REVelation","outlet_id":7,"note":null},{"date":"2017-11-03","outlet_name":"REVelation","outlet_id":7,"note":null}]}