{"meta":{"requests":522,"timestamp":1491340825,"status":200,"message":"Request successful","method_id":1291,"method":{}},"data":{"date":{"week":7,"year":2007,"start":"2007-02-12","end":"2007-02-16"},"outlets":[{"outlet_name":"Brubakers","outlet_id":1,"menu":[{"date":"2007-02-12","day":"Monday","meals":{"lunch":[{"product_name":"Sausage or Hot dog","product_id":null,"diet_type":null}],"dinner":[{"product_name":"A vegetarian dinner option is available","product_id":null,"diet_type":null},{"product_name":"Chicken Stirfry","product_id":null,"diet_type":null}]},"notes":null},{"date":"2007-02-13","day":"Tuesday","meals":{"lunch":[{"product_name":"Turkey Tetrazzini","product_id":105,"diet_type":"Non Vegetarian"}],"dinner":[{"product_name":"1\/4 Chicken Dinner","product_id":null,"diet_type":null},{"product_name":"A vegetarian dinner option is available","product_id":null,"diet_type":null}]},"notes":null},{"date":"2007-02-14","day":"Wednesday","meals":{"lunch":[{"product_name":"Valentine Buffet","product_id":null,"diet_type":null}],"dinner":[{"product_name":"A vegetarian dinner option is available","product_id":null,"diet_type":null},{"product_name":"Salmon","product_id":null,"diet_type":null}]},"notes":null},{"date":"2007-02-15","day":"Thursday","meals":{"lunch":[{"product_name":"Chicken Wings","product_id":null,"diet_type":null}],"dinner":[{"product_name":"A vegetarian dinner option is available","product_id":null,"diet_type":null},{"product_name":"Our Famous Roast Beef Dinner","product_id":null,"diet_type":null}]},"notes":null},{"date":"2007-02-16","day":"Friday","meals":{"lunch":[{"product_name":"Chef's Choice","product_id":null,"diet_type":null}],"dinner":[{"product_name":"A vegetarian dinner option is available","product_id":null,"diet_type":null},{"product_name":"Chef's Choice","product_id":null,"diet_type":null}]},"notes":null}]},{"outlet_name":null,"outlet_id":null,"menu":[{"date":"2007-02-12","day":"Monday","meals":{"lunch":[{"product_name":"Grab a salad","product_id":null,"diet_type":null}],"dinner":[]},"notes":null},{"date":"2007-02-13","day":"Tuesday","meals":{"lunch":[{"product_name":"Panini Heaven","product_id":null,"diet_type":null}],"dinner":[]},"notes":null},{"date":"2007-02-14","day":"Wednesday","meals":{"lunch":[{"product_name":"We have all day breakfast","product_id":null,"diet_type":null}],"dinner":[]},"notes":null},{"date":"2007-02-15","day":"Thursday","meals":{"lunch":[{"product_name":"Try our famous toasted western","product_id":null,"diet_type":null}],"dinner":[]},"notes":null},{"date":"2007-02-16","day":"Friday","meals":{"lunch":[{"product_name":"We have the best onion rings","product_id":null,"diet_type":null}],"dinner":[]},"notes":null}]},{"outlet_name":"Bon Appetit","outlet_id":3,"menu":[{"date":"2007-02-12","day":"Monday","meals":{"lunch":[{"product_name":"Beef with Bamboo Shoots and Dry Mushrooms","product_id":null,"diet_type":null}],"dinner":[{"product_name":"Steamed Chicken Wings with Chinese Mushrooms","product_id":747,"diet_type":"Non Vegetarian"}]},"notes":null},{"date":"2007-02-13","day":"Tuesday","meals":{"lunch":[{"product_name":"BBQ Pork with Tofu","product_id":865,"diet_type":"Non Vegetarian"}],"dinner":[{"product_name":"Beef with Satay Sauce","product_id":738,"diet_type":"Non Vegetarian"}]},"notes":null},{"date":"2007-02-14","day":"Wednesday","meals":{"lunch":[{"product_name":"Sesame Chicken","product_id":685,"diet_type":"Non Vegetarian"}],"dinner":[{"product_name":"BBQ Chicken Wings","product_id":835,"diet_type":"Halal"}]},"notes":null},{"date":"2007-02-15","day":"Thursday","meals":{"lunch":[{"product_name":"Beef Brisket with Potatoes","product_id":748,"diet_type":"Non Vegetarian"}],"dinner":[{"product_name":"Pork Chop with Lemon Grass","product_id":746,"diet_type":"Non Vegetarian"}]},"notes":null},{"date":"2007-02-16","day":"Friday","meals":{"lunch":[{"product_name":"Chef's Choice","product_id":null,"diet_type":null},{"product_name":"Closed @ 2:30pm","product_id":null,"diet_type":null}],"dinner":[]},"notes":null}]},{"outlet_name":"Mudie's","outlet_id":5,"menu":[{"date":"2007-02-12","day":"Monday","meals":{"lunch":[{"product_name":"Chicken Fettuccini","product_id":null,"diet_type":null},{"product_name":"V: Indonesian Sweet & Sour Tempeh","product_id":null,"diet_type":null}],"dinner":[{"product_name":"Chicken Kiev","product_id":null,"diet_type":null},{"product_name":"O-L: Seasonal Vegetables in a Cheese Sauce","product_id":1041,"diet_type":"Vegetarian"}]},"notes":null},{"date":"2007-02-13","day":"Tuesday","meals":{"lunch":[{"product_name":"Lemon Chicken","product_id":742,"diet_type":"Non Vegetarian"},{"product_name":"V: Couscous Royale","product_id":null,"diet_type":null}],"dinner":[{"product_name":"O-L: Cheese Wraparatha","product_id":null,"diet_type":null},{"product_name":"Pork Chop","product_id":1079,"diet_type":"Non Vegetarian"}]},"notes":null},{"date":"2007-02-14","day":"Wednesday","meals":{"lunch":[{"product_name":"Peameal Club Kaiser","product_id":1035,"diet_type":"Non Vegetarian"},{"product_name":"V: Szechwan Tofu","product_id":937,"diet_type":"Vegan"}],"dinner":[{"product_name":"Beef Stir Fry","product_id":null,"diet_type":null},{"product_name":"O-L: Vegetable Lasagna","product_id":889,"diet_type":"Vegetarian"}]},"notes":null},{"date":"2007-02-15","day":"Thursday","meals":{"lunch":[{"product_name":"Swedish Meatballs","product_id":null,"diet_type":null},{"product_name":"V: Brazilian Black Bean Stew","product_id":null,"diet_type":null}],"dinner":[{"product_name":"Chinese New Year","product_id":null,"diet_type":null},{"product_name":"V: Stuffed Green Pepper","product_id":null,"diet_type":null}]},"notes":null},{"date":"2007-02-16","day":"Friday","meals":{"lunch":[{"product_name":"Gyro","product_id":null,"diet_type":null},{"product_name":"V: Falafel","product_id":null,"diet_type":null}],"dinner":[{"product_name":"Grilled Salmon","product_id":1010,"diet_type":"Non Vegetarian"},{"product_name":"O-L: Mediterranean Penne","product_id":null,"diet_type":null}]},"notes":null}]},{"outlet_name":"Festival Fare","outlet_id":6,"menu":[{"date":"2007-02-12","day":"Monday","meals":{"lunch":[{"product_name":"Corned Beef on Rye","product_id":1080,"diet_type":"Non Vegetarian"},{"product_name":"Pork Chop with Coconut Mango Sauce","product_id":null,"diet_type":null}],"dinner":[{"product_name":"A vegetarian option is available daily","product_id":null,"diet_type":null}]},"notes":null},{"date":"2007-02-13","day":"Tuesday","meals":{"lunch":[{"product_name":"Chicken and Ribs","product_id":null,"diet_type":null},{"product_name":"Turkey Pot Pie","product_id":715,"diet_type":"Non Vegetarian"}],"dinner":[{"product_name":"A vegetarian option is available daily","product_id":null,"diet_type":null}]},"notes":null},{"date":"2007-02-14","day":"Wednesday","meals":{"lunch":[{"product_name":"Daily Fish","product_id":null,"diet_type":null},{"product_name":"Pasta Bar","product_id":null,"diet_type":null}],"dinner":[{"product_name":"A vegetarian option is available daily","product_id":null,"diet_type":null}]},"notes":null},{"date":"2007-02-15","day":"Thursday","meals":{"lunch":[{"product_name":"Roast Beef","product_id":null,"diet_type":null},{"product_name":"Sub Bar","product_id":null,"diet_type":null}],"dinner":[{"product_name":"A vegetarian option is available daily","product_id":null,"diet_type":null}]},"notes":null},{"date":"2007-02-16","day":"Friday","meals":{"lunch":[{"product_name":"Daily Fish","product_id":null,"diet_type":null},{"product_name":"Fajita Bar","product_id":null,"diet_type":null}],"dinner":[{"product_name":"A vegetarian option is available daily","product_id":null,"diet_type":null}]},"notes":null}]},{"outlet_name":"REVelation","outlet_id":7,"menu":[{"date":"2007-02-12","day":"Monday","meals":{"lunch":[{"product_name":"Ham and Swiss Croissant","product_id":null,"diet_type":null},{"product_name":"O-L: Jamaican Pattie","product_id":null,"diet_type":null}],"dinner":[{"product_name":"Coconut Tilapia","product_id":928,"diet_type":"Non Vegetarian"},{"product_name":"V: Soy Chicken Stir Fry","product_id":961,"diet_type":"Vegan"}]},"notes":null},{"date":"2007-02-13","day":"Tuesday","meals":{"lunch":[{"product_name":"O-L: Cheese omelette with Salad","product_id":775,"diet_type":"Vegetarian"},{"product_name":"Turkey Schnitzel with Cranberry Salsa","product_id":1076,"diet_type":"Non Vegetarian"}],"dinner":[{"product_name":"V: Greek Style Tofu","product_id":null,"diet_type":null},{"product_name":"Wonton Shrimp","product_id":null,"diet_type":null}]},"notes":null},{"date":"2007-02-14","day":"Wednesday","meals":{"lunch":[{"product_name":"Lover's Lasagna","product_id":null,"diet_type":null},{"product_name":"O-L: Vegetable Lasagna","product_id":889,"diet_type":"Vegetarian"}],"dinner":[{"product_name":"V:  Sweet (Heart) Potato and Bean Ragout","product_id":null,"diet_type":null},{"product_name":"(Cupids), Shrimp Skewer on Rice","product_id":755,"diet_type":"Non Vegetarian"}]},"notes":null},{"date":"2007-02-15","day":"Thursday","meals":{"lunch":[{"product_name":"Chicken Caesar Salad","product_id":66,"diet_type":"Halal"},{"product_name":"O-L: Quiche, Chedder Cheese and Broccoli","product_id":460,"diet_type":"Vegetarian"}],"dinner":[{"product_name":"Pineapple Curry Glazed Pork Loin","product_id":940,"diet_type":"Non Vegetarian"},{"product_name":"V: Stuffed Green Pepper","product_id":null,"diet_type":null}]},"notes":null},{"date":"2007-02-16","day":"Friday","meals":{"lunch":[{"product_name":"Chef's Choice","product_id":null,"diet_type":null},{"product_name":"English Style Fish","product_id":null,"diet_type":null}],"dinner":[{"product_name":"Closed @ 2:00pm","product_id":null,"diet_type":null}]},"notes":null}]}]}}