{"meta":{"requests":201,"timestamp":1491324432,"status":200,"message":"Request successful","method_id":1291,"method":{}},"data":{"date":{"week":27,"year":2010,"start":"2010-07-05","end":"2010-07-09"},"outlets":[{"outlet_name":"Bon Appetit","outlet_id":3,"menu":[{"date":"2010-07-05","day":"Monday","meals":{"lunch":[{"product_name":"Butter Chicken","product_id":1343,"diet_type":"Halal"},{"product_name":"D.C. Chicken Wings with BBQ Sauce","product_id":1964,"diet_type":"Non Vegetarian"},{"product_name":"Vegetable Burger, O-L","product_id":1316,"diet_type":"Vegetarian"}],"dinner":[]},"notes":null},{"date":"2010-07-06","day":"Tuesday","meals":{"lunch":[{"product_name":"DC, Beef with Satay Sauce,","product_id":738,"diet_type":"Non Vegetarian"},{"product_name":"DC, Beef with Snow Peas,","product_id":774,"diet_type":"Non Vegetarian"},{"product_name":"Spaghetti and Tomato Sauce, V","product_id":1324,"diet_type":"Vegan"}],"dinner":[]},"notes":null},{"date":"2010-07-07","day":"Wednesday","meals":{"lunch":[{"product_name":"D.C. Pork Chop with Chili Bean Sauce","product_id":1962,"diet_type":"Non Vegetarian"},{"product_name":"Ginger Chicken","product_id":1627,"diet_type":"Non Vegetarian"},{"product_name":"Spicy Eggplant, V","product_id":1380,"diet_type":"Vegan"}],"dinner":[]},"notes":null},{"date":"2010-07-08","day":"Thursday","meals":{"lunch":[{"product_name":"D.C. BBQ Pork with Tofu","product_id":1965,"diet_type":"Non Vegetarian"},{"product_name":"D.C. Curried Chicken","product_id":1961,"diet_type":"Non Vegetarian"},{"product_name":"Tofu and Chinese Greens, V","product_id":1355,"diet_type":"Vegan"}],"dinner":[]},"notes":null},{"date":"2010-07-09","day":"Friday","meals":{"lunch":[{"product_name":"Chef's Special Closed @ 2:30pm","product_id":null,"diet_type":null}],"dinner":[]},"notes":null}]},{"outlet_name":"Mudie's","outlet_id":5,"menu":[{"date":"2010-07-05","day":"Monday","meals":{"lunch":[{"product_name":"Honey Garlic Chicken","product_id":1483,"diet_type":"Halal"},{"product_name":"Native Valley Cous Cous, V","product_id":918,"diet_type":"Vegan"},{"product_name":"Sweet and Sour Pork","product_id":null,"diet_type":null}],"dinner":[{"product_name":"Cheese Cannelloni, O-L","product_id":1034,"diet_type":"Vegetarian"},{"product_name":"Roast Beef","product_id":1312,"diet_type":"Halal"},{"product_name":"Roast Stuffed Cornish Game Hen","product_id":2111,"diet_type":"Non Vegetarian"}]},"notes":null},{"date":"2010-07-06","day":"Tuesday","meals":{"lunch":[{"product_name":"Herb Crusted Salmon","product_id":1215,"diet_type":"Non Vegetarian"},{"product_name":"Mudies Sandwich, Greek Chicken Foccacia","product_id":null,"diet_type":null},{"product_name":"Sweet and Sour Tofu, V","product_id":null,"diet_type":null}],"dinner":[{"product_name":"Chicken Breast with Maple Mustard Glaze","product_id":2163,"diet_type":"Halal"},{"product_name":"Marinated Roast Lamb","product_id":2161,"diet_type":"Non Vegetarian"},{"product_name":"Rocky Mountain Vegetable Stew, V","product_id":1275,"diet_type":"Vegan"}]},"notes":null},{"date":"2010-07-07","day":"Wednesday","meals":{"lunch":[{"product_name":"Beef Stir Fry","product_id":1371,"diet_type":"Halal"},{"product_name":"Chinese Dumplings","product_id":877,"diet_type":"Vegan"},{"product_name":"Mexican Chopped Salad with Chicken","product_id":2160,"diet_type":"Halal"}],"dinner":[{"product_name":"Garlic Herb Tilapia","product_id":1919,"diet_type":"Halal"},{"product_name":"Matter Paneer","product_id":null,"diet_type":null},{"product_name":"Pork Loin","product_id":972,"diet_type":"Non Vegetarian"}]},"notes":null},{"date":"2010-07-08","day":"Thursday","meals":{"lunch":[{"product_name":"Guinness BBQ Wings","product_id":2159,"diet_type":"Halal"},{"product_name":"Perogies, O-L","product_id":1327,"diet_type":"Vegetarian"},{"product_name":"Tex Mex Chipotle Sloppy Joe","product_id":2162,"diet_type":"Halal"}],"dinner":[{"product_name":"Chicken Kebab","product_id":2106,"diet_type":"Non Vegetarian"},{"product_name":"Mudies, New York Steak w\/ Onion and Mushroom","product_id":1773,"diet_type":"Non Vegetarian"},{"product_name":"Stuffed Pasta Shells w\/ Pesto Sauce","product_id":null,"diet_type":null}]},"notes":null},{"date":"2010-07-09","day":"Friday","meals":{"lunch":[{"product_name":"Island Treasure Sweet Potato and Bean Ragout, V","product_id":null,"diet_type":null},{"product_name":"Shanghai Noodles,","product_id":666,"diet_type":"Non Vegetarian"},{"product_name":"Turkey Burger w\/ Roasted Red Pepper Relish","product_id":2164,"diet_type":"Halal"}],"dinner":[{"product_name":"Ribs, BBQ Style","product_id":231,"diet_type":"Non Vegetarian"},{"product_name":"Vegetable Kebab","product_id":871,"diet_type":"Vegan"}]},"notes":null}]}]}}